[{"name":"Elevated Tech","DeviceList":[{"account_id":"226825","deviceDesc":"1290969","name":"ET-Smartone-Demo","deviceID":"232000"},{"account_id":"226825","deviceDesc":"352054051698190","name":"ET-OBD-Demo-Kelly","deviceID":"1085149"},{"account_id":"226825","deviceDesc":"15987","name":"parth","deviceID":"7238919"},{"account_id":"226825","deviceDesc":"9000","name":"tata ttt","deviceID":"7238920"}]},{"name":"Wolf Pack Rentals","DeviceList":[{"account_id":"226860","deviceDesc":"1280673","name":"T113","deviceID":"232208"},{"account_id":"226860","deviceDesc":"1286784","name":"T028","deviceID":"232204"},{"account_id":"226860","deviceDesc":"1289739","name":"T173","deviceID":"232114"},{"account_id":"226860","deviceDesc":"1292342","name":"T101","deviceID":"232099"},{"account_id":"226860","deviceDesc":"1291919","name":"T207","deviceID":"232123"},{"account_id":"226860","deviceDesc":"1286317","name":"T209","deviceID":"232203"},{"account_id":"226860","deviceDesc":"1286236","name":"T094","deviceID":"232211"},{"account_id":"226860","deviceDesc":"1285930","name":"T205","deviceID":"232063"},{"account_id":"226860","deviceDesc":"1292019","name":"T501","deviceID":"232115"},{"account_id":"226860","deviceDesc":"1290862","name":"T203","deviceID":"232131"},{"account_id":"226860","deviceDesc":"1286981","name":"T199","deviceID":"232101"},{"account_id":"226860","deviceDesc":"1286606","name":"T096","deviceID":"232060"},{"account_id":"226860","deviceDesc":"1283972","name":"T080","deviceID":"232050"},{"account_id":"226860","deviceDesc":"1279704","name":"T197","deviceID":"232209"},{"account_id":"226860","deviceDesc":"1291677","name":"T206","deviceID":"232109"},{"account_id":"226860","deviceDesc":"1291230","name":"T075","deviceID":"232093"},{"account_id":"226860","deviceDesc":"1286789","name":"T261","deviceID":"232068"},{"account_id":"226860","deviceDesc":"1286382","name":"T139","deviceID":"232218"},{"account_id":"226860","deviceDesc":"1286875","name":"T268","deviceID":"232219"},{"account_id":"226860","deviceDesc":"1288715","name":"T514","deviceID":"232083"},{"account_id":"226860","deviceDesc":"1286719","name":"T152","deviceID":"232049"},{"account_id":"226860","deviceDesc":"1292262","name":"T135","deviceID":"232098"},{"account_id":"226860","deviceDesc":"1283978","name":"T259","deviceID":"232056"},{"account_id":"226860","deviceDesc":"1286018","name":"T214","deviceID":"232205"},{"account_id":"226860","deviceDesc":"1291194","name":"T146","deviceID":"232129"},{"account_id":"226860","deviceDesc":"1287822","name":"T513","deviceID":"232126"},{"account_id":"226860","deviceDesc":"1281113","name":"T043","deviceID":"232066"},{"account_id":"226860","deviceDesc":"1290980","name":"T175","deviceID":"232130"},{"account_id":"226860","deviceDesc":"1284624","name":"T110","deviceID":"232069"},{"account_id":"226860","deviceDesc":"1286265","name":"T179","deviceID":"232054"},{"account_id":"226860","deviceDesc":"1282796","name":"T032","deviceID":"232064"},{"account_id":"226860","deviceDesc":"1284366","name":"T138","deviceID":"232214"},{"account_id":"226860","deviceDesc":"1291363","name":"T208","deviceID":"232172"},{"account_id":"226860","deviceDesc":"1286475","name":"T262","deviceID":"232047"},{"account_id":"226860","deviceDesc":"1286489","name":"T084","deviceID":"232046"},{"account_id":"226860","deviceDesc":"1291662","name":"T239","deviceID":"232078"},{"account_id":"226860","deviceDesc":"1286381","name":"T020","deviceID":"232217"},{"account_id":"226860","deviceDesc":"1280593","name":"T159","deviceID":"232195"},{"account_id":"226860","deviceDesc":"1289461","name":"T508","deviceID":"232185"},{"account_id":"226860","deviceDesc":"1285888","name":"T200","deviceID":"232057"},{"account_id":"226860","deviceDesc":"1292536","name":"T021","deviceID":"232079"},{"account_id":"226860","deviceDesc":"1282875","name":"T211","deviceID":"232055"},{"account_id":"226860","deviceDesc":"1287844","name":"T058","deviceID":"232125"},{"account_id":"226860","deviceDesc":"1283852","name":"T228","deviceID":"232226"},{"account_id":"226860","deviceDesc":"1292928","name":"T220","deviceID":"232096"},{"account_id":"226860","deviceDesc":"1286772","name":"T137","deviceID":"232051"},{"account_id":"226860","deviceDesc":"1280098","name":"T233","deviceID":"232223"},{"account_id":"226860","deviceDesc":"1280881","name":"T153","deviceID":"232221"},{"account_id":"226860","deviceDesc":"1287776","name":"T270","deviceID":"232102"},{"account_id":"226860","deviceDesc":"1287977","name":"T149","deviceID":"232077"},{"account_id":"226860","deviceDesc":"1289589","name":"T033","deviceID":"232122"},{"account_id":"226860","deviceDesc":"1285726","name":"T134","deviceID":"232052"},{"account_id":"226860","deviceDesc":"1289922","name":"T204","deviceID":"232103"},{"account_id":"226860","deviceDesc":"1286857","name":"T145","deviceID":"232058"},{"account_id":"226860","deviceDesc":"1292337","name":"T251","deviceID":"232095"},{"account_id":"226860","deviceDesc":"1292106","name":"T516","deviceID":"232087"},{"account_id":"226860","deviceDesc":"1292532","name":"T187","deviceID":"232082"},{"account_id":"226860","deviceDesc":"1289080","name":"T064","deviceID":"232186"},{"account_id":"226860","deviceDesc":"1288043","name":"T024","deviceID":"232184"},{"account_id":"226860","deviceDesc":"1287148","name":"T163","deviceID":"232104"},{"account_id":"226860","deviceDesc":"1287787","name":"T248","deviceID":"232084"},{"account_id":"226860","deviceDesc":"1291604","name":"T402","deviceID":"232105"},{"account_id":"226860","deviceDesc":"1287625","name":"T111","deviceID":"232097"},{"account_id":"226860","deviceDesc":"1284577","name":"T507","deviceID":"232053"},{"account_id":"226860","deviceDesc":"1290566","name":"T510","deviceID":"232180"},{"account_id":"226860","deviceDesc":"1284373","name":"T055","deviceID":"232200"},{"account_id":"226860","deviceDesc":"1284588","name":"T164","deviceID":"232048"},{"account_id":"226860","deviceDesc":"1285235","name":"T151","deviceID":"232229"},{"account_id":"226860","deviceDesc":"1289931","name":"T066-O","deviceID":"232076"},{"account_id":"226860","deviceDesc":"1289786","name":"T218","deviceID":"232080"},{"account_id":"226860","deviceDesc":"1289527","name":"T168","deviceID":"232089"},{"account_id":"226860","deviceDesc":"1291602","name":"T189","deviceID":"232187"},{"account_id":"226860","deviceDesc":"1284514","name":"T517","deviceID":"232222"},{"account_id":"226860","deviceDesc":"1280938","name":"T148","deviceID":"232210"},{"account_id":"226860","deviceDesc":"1289778","name":"T127","deviceID":"232100"},{"account_id":"226860","deviceDesc":"1290849","name":"T071","deviceID":"232177"},{"account_id":"226860","deviceDesc":"1286376","name":"T219","deviceID":"232228"},{"account_id":"226860","deviceDesc":"1292322","name":"T158","deviceID":"232192"},{"account_id":"226860","deviceDesc":"1289950","name":"T509","deviceID":"232113"},{"account_id":"226860","deviceDesc":"1288426","name":"T227","deviceID":"232094"},{"account_id":"226860","deviceDesc":"1286044","name":"T104","deviceID":"232220"},{"account_id":"226860","deviceDesc":"1292355","name":"T225","deviceID":"232124"},{"account_id":"226860","deviceDesc":"1288236","name":"T504","deviceID":"232106"},{"account_id":"226860","deviceDesc":"1287854","name":"T500","deviceID":"232088"},{"account_id":"226860","deviceDesc":"1286054","name":"T403","deviceID":"232213"},{"account_id":"226860","deviceDesc":"1285976","name":"T400","deviceID":"232199"},{"account_id":"226860","deviceDesc":"1292028","name":"T041","deviceID":"643659"},{"account_id":"226860","deviceDesc":"1290079","name":"T144","deviceID":"643381"},{"account_id":"226860","deviceDesc":"1290066","name":"G37","deviceID":"643378"},{"account_id":"226860","deviceDesc":"1291463","name":"T260","deviceID":"643581"},{"account_id":"226860","deviceDesc":"1290385","name":"T074","deviceID":"643423"},{"account_id":"226860","deviceDesc":"1292357","name":"T291","deviceID":"643689"},{"account_id":"226860","deviceDesc":"1290436","name":"T124","deviceID":"643442"},{"account_id":"226860","deviceDesc":"1290286","name":"T136","deviceID":"643409"},{"account_id":"226860","deviceDesc":"1292385","name":"T085","deviceID":"643691"},{"account_id":"226860","deviceDesc":"1290028","name":"T506","deviceID":"643339"},{"account_id":"226860","deviceDesc":"1290034","name":" T503 ","deviceID":"643341"},{"account_id":"226860","deviceDesc":"1292024","name":"T107","deviceID":"643646"},{"account_id":"226860","deviceDesc":"1290051","name":"G39","deviceID":"643360"},{"account_id":"226860","deviceDesc":"1290548","name":"T511","deviceID":"643488"},{"account_id":"226860","deviceDesc":"1291714","name":"T250","deviceID":"643586"},{"account_id":"226860","deviceDesc":"1291825","name":"T524","deviceID":"643602"},{"account_id":"226860","deviceDesc":"1291784","name":"T407","deviceID":"643599"},{"account_id":"226860","deviceDesc":"1290037","name":"T515","deviceID":"643348"},{"account_id":"226860","deviceDesc":"1292032","name":"T521","deviceID":"643660"},{"account_id":"226860","deviceDesc":"1290475","name":"T195","deviceID":"643477"},{"account_id":"226860","deviceDesc":"1290301","name":"T157","deviceID":"643420"},{"account_id":"226860","deviceDesc":"1292082","name":"T088","deviceID":"643686"},{"account_id":"226860","deviceDesc":"1290164","name":"T525","deviceID":"643398"},{"account_id":"226860","deviceDesc":"1290434","name":"T284","deviceID":"643438"},{"account_id":"226860","deviceDesc":"1292066","name":"T030","deviceID":"643669"},{"account_id":"226860","deviceDesc":"1290158","name":"T212","deviceID":"643390"},{"account_id":"226860","deviceDesc":"1292068","name":"T194","deviceID":"643674"},{"account_id":"226860","deviceDesc":"1292074","name":"T095","deviceID":"643678"},{"account_id":"226860","deviceDesc":"1290439","name":"T077","deviceID":"643461"},{"account_id":"226860","deviceDesc":"1291876","name":"G41","deviceID":"643624"},{"account_id":"226860","deviceDesc":"1290060","name":"T155","deviceID":"643373"},{"account_id":"226860","deviceDesc":"1292079","name":"T520","deviceID":"643681"},{"account_id":"226860","deviceDesc":"1292338","name":"T126","deviceID":"643687"},{"account_id":"226860","deviceDesc":"1290041","name":"T190","deviceID":"643355"},{"account_id":"226860","deviceDesc":"1290627","name":"T267","deviceID":"643491"},{"account_id":"226860","deviceDesc":"1290429","name":"T170","deviceID":"643426"},{"account_id":"226860","deviceDesc":"1284758","name":"T174","deviceID":"232212"},{"account_id":"226860","deviceDesc":"1277348","name":"T129","deviceID":"232196"},{"account_id":"226860","deviceDesc":"1301677","name":"CQ021","deviceID":"1607934"},{"account_id":"226860","deviceDesc":"1298810","name":"1298810","deviceID":"1603034"},{"account_id":"226860","deviceDesc":"1301526","name":"T106","deviceID":"1607847"},{"account_id":"226860","deviceDesc":"1300502","name":"T246","deviceID":"1603806"},{"account_id":"226860","deviceDesc":"1301641","name":"T236","deviceID":"1607897"},{"account_id":"226860","deviceDesc":"1286609","name":"T154","deviceID":"232061"},{"account_id":"226860","deviceDesc":"1282815","name":"T116","deviceID":"232067"},{"account_id":"226860","deviceDesc":"1290860","name":"CQ008","deviceID":"1602895"},{"account_id":"226860","deviceDesc":"1291621","name":"T290","deviceID":"1602927"},{"account_id":"226860","deviceDesc":"1291133","name":"F005","deviceID":"1602898"},{"account_id":"226860","deviceDesc":"1301133","name":"F006","deviceID":"1604248"},{"account_id":"226860","deviceDesc":"1301291","name":"CQ019","deviceID":"1607653"},{"account_id":"226860","deviceDesc":"1299606","name":"SMC004","deviceID":"1603355"},{"account_id":"226860","deviceDesc":"1301681","name":"F010","deviceID":"1607951"},{"account_id":"226860","deviceDesc":"1301402","name":"T087","deviceID":"1607761"},{"account_id":"226860","deviceDesc":"1301283","name":"T279","deviceID":"1607614"},{"account_id":"226860","deviceDesc":"1301840","name":"SMC009","deviceID":"1608196"},{"account_id":"226860","deviceDesc":"1301674","name":"CO17","deviceID":"1607925"},{"account_id":"226860","deviceDesc":"1300469","name":"T185","deviceID":"1603766"},{"account_id":"226860","deviceDesc":"1300636","name":"T202","deviceID":"1603899"},{"account_id":"226860","deviceDesc":"1300765","name":"T232","deviceID":"1603984"},{"account_id":"226860","deviceDesc":"1300626","name":"1300626","deviceID":"1603896"},{"account_id":"226860","deviceDesc":"1298969","name":"T234","deviceID":"1603074"},{"account_id":"226860","deviceDesc":"1288874","name":"CQ022","deviceID":"1602793"},{"account_id":"226860","deviceDesc":"1301298","name":"CQ010","deviceID":"1607668"},{"account_id":"226860","deviceDesc":"1301176","name":"CQ037","deviceID":"1604276"},{"account_id":"226860","deviceDesc":"1298963","name":"T274","deviceID":"1603067"},{"account_id":"226860","deviceDesc":"1290759","name":"T160","deviceID":"1602869"},{"account_id":"226860","deviceDesc":"1301486","name":"T128","deviceID":"1607825"},{"account_id":"226860","deviceDesc":"1299607","name":"T253","deviceID":"1603373"},{"account_id":"226860","deviceDesc":"1300664","name":"SMC005","deviceID":"1603938"},{"account_id":"226860","deviceDesc":"1288225","name":"T196","deviceID":"1602768"},{"account_id":"226860","deviceDesc":"1301427","name":"1301427","deviceID":"1607822"},{"account_id":"226860","deviceDesc":"1300007","name":"T230","deviceID":"1603416"},{"account_id":"226860","deviceDesc":"1301320","name":"1301320","deviceID":"1607694"},{"account_id":"226860","deviceDesc":"1301489","name":"1301489","deviceID":"1607836"},{"account_id":"226860","deviceDesc":"1301668","name":"T256","deviceID":"1607908"},{"account_id":"226860","deviceDesc":"1289824","name":"T184","deviceID":"1602824"},{"account_id":"226860","deviceDesc":"1301551","name":"T162","deviceID":"1607866"},{"account_id":"226860","deviceDesc":"1301687","name":"CQ024","deviceID":"1607990"},{"account_id":"226860","deviceDesc":"1301108","name":"SMC007","deviceID":"1604233"},{"account_id":"226860","deviceDesc":"1301685","name":"CQ011","deviceID":"1607970"},{"account_id":"226860","deviceDesc":"1288251","name":"Removed- T275","deviceID":"1602784"},{"account_id":"226860","deviceDesc":"1284619","name":"T216","deviceID":"232059"},{"account_id":"226860","deviceDesc":"1290738","name":"T045","deviceID":"643511"},{"account_id":"226860","deviceDesc":"1290731","name":"T105","deviceID":"643506"},{"account_id":"226860","deviceDesc":"1290976","name":"T076","deviceID":"643534"},{"account_id":"226860","deviceDesc":"1291042","name":"T122-S","deviceID":"643544"},{"account_id":"226860","deviceDesc":"1290871","name":"T264","deviceID":"643533"},{"account_id":"226860","deviceDesc":"1290799","name":"T042","deviceID":"643532"},{"account_id":"226860","deviceDesc":"1290985","name":"T165","deviceID":"643542"},{"account_id":"226860","deviceDesc":"1291350","name":"T193","deviceID":"643558"},{"account_id":"226860","deviceDesc":"1292635","name":"T406","deviceID":"643697"},{"account_id":"226860","deviceDesc":"1292506","name":"T249","deviceID":"643695"},{"account_id":"226860","deviceDesc":"1292387","name":"T091","deviceID":"643692"},{"account_id":"226860","deviceDesc":"1291051","name":"T005-S","deviceID":"643552"},{"account_id":"226860","deviceDesc":"1292646","name":"T012","deviceID":"643698"},{"account_id":"226860","deviceDesc":"1292508","name":"T089","deviceID":"643696"},{"account_id":"226860","deviceDesc":"1291832","name":"T057","deviceID":"643606"},{"account_id":"226860","deviceDesc":"1291045","name":"T519","deviceID":"643547"},{"account_id":"226860","deviceDesc":"1291462","name":"T082","deviceID":"643574"},{"account_id":"226860","deviceDesc":"1291717","name":"T086","deviceID":"643588"},{"account_id":"226860","deviceDesc":"1288194","name":"T201","deviceID":"643196"},{"account_id":"226860","deviceDesc":"1291833","name":"T118","deviceID":"643621"},{"account_id":"226860","deviceDesc":"1291762","name":"T052","deviceID":"643594"},{"account_id":"226860","deviceDesc":"1291375","name":"T072","deviceID":"643567"},{"account_id":"226860","deviceDesc":"1301327","name":"SMC008","deviceID":"1607721"},{"account_id":"226860","deviceDesc":"1300615","name":"CQ044","deviceID":"1603863"},{"account_id":"226860","deviceDesc":"1300720","name":"T013","deviceID":"1603956"},{"account_id":"226860","deviceDesc":"1300472","name":"T282","deviceID":"1603771"},{"account_id":"226860","deviceDesc":"1301173","name":"CQ013","deviceID":"1604259"},{"account_id":"226860","deviceDesc":"1300495","name":"T078-O","deviceID":"1603795"},{"account_id":"226860","deviceDesc":"1300909","name":"CQ040","deviceID":"1604094"},{"account_id":"226860","deviceDesc":"1300721","name":"SMC011","deviceID":"1603975"},{"account_id":"226860","deviceDesc":"1301002","name":"CQ049","deviceID":"1604182"},{"account_id":"226860","deviceDesc":"1300786","name":"CQ039","deviceID":"1604052"},{"account_id":"226860","deviceDesc":"1301386","name":"CQ048","deviceID":"1607726"},{"account_id":"226860","deviceDesc":"1301233","name":"T171","deviceID":"1604335"},{"account_id":"226860","deviceDesc":"1300970","name":"T254","deviceID":"1604149"},{"account_id":"226860","deviceDesc":"1301038","name":"SMC010","deviceID":"1604222"},{"account_id":"226860","deviceDesc":"1300553","name":"1300553","deviceID":"1603834"},{"account_id":"226860","deviceDesc":"1291964","name":"T192-S","deviceID":"1602958"},{"account_id":"226860","deviceDesc":"1298763","name":"CQ016","deviceID":"1602988"},{"account_id":"226860","deviceDesc":"1292735","name":"T150-S","deviceID":"1602968"},{"account_id":"226860","deviceDesc":"1300802","name":"1300802","deviceID":"1604065"},{"account_id":"226860","deviceDesc":"1301177","name":"CQ042","deviceID":"1604287"},{"account_id":"226860","deviceDesc":"1300613","name":"CQ033","deviceID":"1603842"},{"account_id":"226860","deviceDesc":"1291275","name":"CQ046","deviceID":"1602903"},{"account_id":"226860","deviceDesc":"1292725","name":"T053-S","deviceID":"1602965"},{"account_id":"226860","deviceDesc":"1300911","name":"1300911","deviceID":"1604103"},{"account_id":"226860","deviceDesc":"1300912","name":"1300912","deviceID":"1604114"},{"account_id":"226860","deviceDesc":"1300919","name":"1300919","deviceID":"1604130"},{"account_id":"226860","deviceDesc":"1300917","name":"1300917","deviceID":"1604121"},{"account_id":"226860","deviceDesc":"1300618","name":"CQ030","deviceID":"1603875"},{"account_id":"226860","deviceDesc":"1291638","name":"F007","deviceID":"1602936"},{"account_id":"226860","deviceDesc":"1301179","name":"T287","deviceID":"1604290"},{"account_id":"226860","deviceDesc":"1300485","name":"T186","deviceID":"1603785"},{"account_id":"226860","deviceDesc":"1301222","name":"CQ027","deviceID":"1604322"},{"account_id":"226860","deviceDesc":"1300828","name":"G46","deviceID":"1604085"},{"account_id":"226860","deviceDesc":"1301300","name":"1301300","deviceID":"1607677"},{"account_id":"226860","deviceDesc":"1301181","name":"CQ043","deviceID":"1604309"},{"account_id":"226860","deviceDesc":"1291441","name":"T223","deviceID":"1602920"},{"account_id":"226860","deviceDesc":"1292737","name":"T112","deviceID":"643707"},{"account_id":"226860","deviceDesc":"1286771","name":"T103","deviceID":"232070"},{"account_id":"226860","deviceDesc":"1300056","name":"CQ014","deviceID":"1603454"},{"account_id":"226860","deviceDesc":"1299074","name":"T245","deviceID":"1603141"},{"account_id":"226860","deviceDesc":"1300261","name":"T244","deviceID":"1603514"},{"account_id":"226860","deviceDesc":"1300454","name":"CQ034","deviceID":"1603737"},{"account_id":"226860","deviceDesc":"1300272","name":"SMC003","deviceID":"1603581"},{"account_id":"226860","deviceDesc":"1300054","name":"CQ031","deviceID":"1603441"},{"account_id":"226860","deviceDesc":"1299605","name":"T147","deviceID":"1603337"},{"account_id":"226860","deviceDesc":"1300016","name":"CQ028","deviceID":"1603423"},{"account_id":"226860","deviceDesc":"1300270","name":"T235","deviceID":"1603564"},{"account_id":"226860","deviceDesc":"1299086","name":"T198","deviceID":"1603232"},{"account_id":"226860","deviceDesc":"1299180","name":"T180","deviceID":"1603264"},{"account_id":"226860","deviceDesc":"1299608","name":"T271","deviceID":"1603384"},{"account_id":"226860","deviceDesc":"1300235","name":"F004","deviceID":"1603497"},{"account_id":"226860","deviceDesc":"1300424","name":"T237","deviceID":"1603695"},{"account_id":"226860","deviceDesc":"1300001","name":"CQ017","deviceID":"1603405"},{"account_id":"226860","deviceDesc":"1299056","name":"T178","deviceID":"1603104"},{"account_id":"226860","deviceDesc":"1299604","name":"T167","deviceID":"1603330"},{"account_id":"226860","deviceDesc":"1299185","name":"T231","deviceID":"1603279"},{"account_id":"226860","deviceDesc":"1300041","name":"CQ012","deviceID":"1603432"},{"account_id":"226860","deviceDesc":"1299077","name":"T181","deviceID":"1603176"},{"account_id":"226860","deviceDesc":"1300305","name":"1300305","deviceID":"1603669"},{"account_id":"226860","deviceDesc":"1299596","name":"T281","deviceID":"1603311"},{"account_id":"226860","deviceDesc":"1299078","name":"T278","deviceID":"1603194"},{"account_id":"226860","deviceDesc":"1300974","name":"T141","deviceID":"1604156"},{"account_id":"226860","deviceDesc":"1299186","name":"G45","deviceID":"1603286"},{"account_id":"226860","deviceDesc":"1300264","name":"T238","deviceID":"1603542"},{"account_id":"226860","deviceDesc":"1300262","name":"F012","deviceID":"1603526"},{"account_id":"226860","deviceDesc":"1300294","name":"G44","deviceID":"1603637"},{"account_id":"226860","deviceDesc":"1300825","name":"F014","deviceID":"1604072"},{"account_id":"226860","deviceDesc":"1301262","name":"T073","deviceID":"1604350"},{"account_id":"226860","deviceDesc":"1301032","name":"T276","deviceID":"1604217"},{"account_id":"226860","deviceDesc":"1286687","name":"T288","deviceID":"1602718"},{"account_id":"226860","deviceDesc":"1300063","name":"T131","deviceID":"1603469"},{"account_id":"226860","deviceDesc":"1300296","name":"1300296","deviceID":"1603655"},{"account_id":"226860","deviceDesc":"1300440","name":"1300440","deviceID":"1603704"},{"account_id":"226860","deviceDesc":"1300269","name":"CQ036","deviceID":"1603555"},{"account_id":"226860","deviceDesc":"1300642","name":"1300642","deviceID":"1603928"},{"account_id":"226860","deviceDesc":"1301003","name":"CQ018","deviceID":"1604191"},{"account_id":"226860","deviceDesc":"1300293","name":"F015","deviceID":"1603622"},{"account_id":"226860","deviceDesc":"1301031","name":"T182","deviceID":"1604204"},{"account_id":"226860","deviceDesc":"1300066","name":"CQ020","deviceID":"1603490"},{"account_id":"226860","deviceDesc":"1300983","name":"CQ041","deviceID":"1604163"},{"account_id":"226860","deviceDesc":"1300306","name":"G42","deviceID":"1603684"},{"account_id":"226860","deviceDesc":"1299084","name":"T240","deviceID":"1603218"},{"account_id":"226860","deviceDesc":"1292042","name":"T215","deviceID":"232075"},{"account_id":"226860","deviceDesc":"1290808","name":"T114-O","deviceID":"232110"},{"account_id":"226860","deviceDesc":"1291029","name":"T213","deviceID":"232090"},{"account_id":"226860","deviceDesc":"1287700","name":"T266","deviceID":"232081"},{"account_id":"226860","deviceDesc":"1290753","name":"T090","deviceID":"643525"},{"account_id":"226860","deviceDesc":"1291336","name":"T062","deviceID":"643553"},{"account_id":"226860","deviceDesc":"1287274","name":"F002-S","deviceID":"1602735"},{"account_id":"226860","deviceDesc":"1287507","name":"T177","deviceID":"643179"},{"account_id":"226860","deviceDesc":"1289577","name":"T065","deviceID":"643233"},{"account_id":"226860","deviceDesc":"1287496","name":"T010","deviceID":"643142"},{"account_id":"226860","deviceDesc":"1288869","name":"T224","deviceID":"643199"},{"account_id":"226860","deviceDesc":"1288452","name":"T109","deviceID":"643198"},{"account_id":"226860","deviceDesc":"1287562","name":"T123","deviceID":"643189"},{"account_id":"226860","deviceDesc":"1288890","name":"T093","deviceID":"643204"},{"account_id":"226860","deviceDesc":"1287503","name":"T265","deviceID":"643174"},{"account_id":"226860","deviceDesc":"1289553","name":"T518","deviceID":"643217"},{"account_id":"226860","deviceDesc":"1289853","name":"T140","deviceID":"643265"},{"account_id":"226860","deviceDesc":"1286039","name":"T263","deviceID":"232227"},{"account_id":"226860","deviceDesc":"1289116","name":"T405","deviceID":"643214"},{"account_id":"226860","deviceDesc":"1289580","name":"T522","deviceID":"643238"},{"account_id":"226860","deviceDesc":"1287501","name":"T108","deviceID":"643157"},{"account_id":"226860","deviceDesc":"1289828","name":"T133","deviceID":"643242"},{"account_id":"226860","deviceDesc":"1288022","name":"T119","deviceID":"643194"},{"account_id":"226860","deviceDesc":"1289795","name":"T092","deviceID":"643241"},{"account_id":"226860","deviceDesc":"1289550","name":"T512","deviceID":"643216"},{"account_id":"226860","deviceDesc":"1289574","name":"T289","deviceID":"643224"},{"account_id":"226860","deviceDesc":"1287563","name":"T130","deviceID":"643193"},{"account_id":"226860","deviceDesc":"1289540","name":"T523","deviceID":"643215"},{"account_id":"226860","deviceDesc":"1289000","name":"T120","deviceID":"643205"},{"account_id":"226860","deviceDesc":"1299051","name":"T257","deviceID":"1603081"},{"account_id":"226860","deviceDesc":"1298838","name":"T142","deviceID":"1603055"},{"account_id":"226860","deviceDesc":"1288761","name":"T169","deviceID":"1602786"},{"account_id":"226860","deviceDesc":"1291653","name":"F008","deviceID":"1602951"},{"account_id":"226860","deviceDesc":"1299550","name":"T241","deviceID":"1603300"},{"account_id":"226860","deviceDesc":"1289830","name":"T098","deviceID":"643249"},{"account_id":"226860","deviceDesc":"1289831","name":"T132","deviceID":"643250"},{"account_id":"226860","deviceDesc":"1298758","name":"T054","deviceID":"1602977"},{"account_id":"226860","deviceDesc":"1290152","name":"T166","deviceID":"1602858"},{"account_id":"226860","deviceDesc":"1289846","name":"T285","deviceID":"643259"},{"account_id":"226860","deviceDesc":"1289850","name":"T217","deviceID":"643264"},{"account_id":"226860","deviceDesc":"1298772","name":"F013","deviceID":"1603024"},{"account_id":"226860","deviceDesc":"1299254","name":"T280","deviceID":"1603293"},{"account_id":"226860","deviceDesc":"1289024","name":"T222","deviceID":"1602815"},{"account_id":"226860","deviceDesc":"1299603","name":"T226","deviceID":"1603325"},{"account_id":"226860","deviceDesc":"1289967","name":"T286","deviceID":"643314"},{"account_id":"226860","deviceDesc":"1288953","name":"CQ015","deviceID":"1602810"},{"account_id":"226860","deviceDesc":"1287867","name":"T172","deviceID":"1602757"},{"account_id":"226860","deviceDesc":"1299598","name":"T083","deviceID":"1603316"},{"account_id":"226860","deviceDesc":"1298769","name":"T016-J","deviceID":"1603001"},{"account_id":"226860","deviceDesc":"1298808","name":"CQ045","deviceID":"1603033"},{"account_id":"226860","deviceDesc":"1290826","name":"F009","deviceID":"1602876"},{"account_id":"226860","deviceDesc":"1289966","name":"T176","deviceID":"643284"},{"account_id":"226860","deviceDesc":"1298930","name":"T115","deviceID":"1603062"},{"account_id":"226860","deviceDesc":"1289930","name":"T191","deviceID":"1602849"},{"account_id":"226860","deviceDesc":"1283982","name":"T242","deviceID":"232065"},{"account_id":"226860","deviceDesc":"1289933","name":"T505","deviceID":"643270"},{"account_id":"226860","deviceDesc":"1290462","name":"T404","deviceID":"643470"},{"account_id":"226860","deviceDesc":"1292001","name":"T401","deviceID":"232183"},{"account_id":"226860","deviceDesc":"1290437","name":"T040","deviceID":"643449"},{"account_id":"226860","deviceDesc":"1290013","name":"T269","deviceID":"643327"},{"account_id":"226860","deviceDesc":"1289968","name":"T161","deviceID":"643323"},{"account_id":"226860","deviceDesc":"1290023","name":"T117","deviceID":"643332"},{"account_id":"226860","deviceDesc":"1290274","name":"G38","deviceID":"643404"},{"account_id":"226860","deviceDesc":"1289987","name":"T526","deviceID":"643324"},{"account_id":"226860","deviceDesc":"1290438","name":"T097","deviceID":"643456"},{"account_id":"226860","deviceDesc":"1301841","name":"1301841","deviceID":"1608230"},{"account_id":"226860","deviceDesc":"1302820","name":"CQ047","deviceID":"1609706"},{"account_id":"226860","deviceDesc":"1302775","name":"1302775","deviceID":"1609480"},{"account_id":"226860","deviceDesc":"1302830","name":"T183","deviceID":"1609778"},{"account_id":"226860","deviceDesc":"1304054","name":"CQ029","deviceID":"1610023"},{"account_id":"226860","deviceDesc":"1304059","name":"CQ032","deviceID":"1610062"},{"account_id":"226860","deviceDesc":"1302767","name":"T255","deviceID":"1609463"},{"account_id":"226860","deviceDesc":"1304056","name":"CQ026","deviceID":"1610034"},{"account_id":"226860","deviceDesc":"1303856","name":"1303856","deviceID":"1609950"},{"account_id":"226860","deviceDesc":"1302802","name":"CO19","deviceID":"1609669"},{"account_id":"226860","deviceDesc":"1303962","name":"1303962","deviceID":"1609978"},{"account_id":"226860","deviceDesc":"1302833","name":"G11","deviceID":"1609819"},{"account_id":"226860","deviceDesc":"1304060","name":"T258","deviceID":"1610071"},{"account_id":"226860","deviceDesc":"1304001","name":"T247","deviceID":"1610005"},{"account_id":"226860","deviceDesc":"1303844","name":"T275-S","deviceID":"1609937"},{"account_id":"226860","deviceDesc":"1304091","name":"1304091","deviceID":"1610089"},{"account_id":"226860","deviceDesc":"1304042","name":"T252","deviceID":"1610014"},{"account_id":"226860","deviceDesc":"1303630","name":"T277","deviceID":"1609886"},{"account_id":"226860","deviceDesc":"1304062","name":"CQ038","deviceID":"1610080"},{"account_id":"226860","deviceDesc":"1302801","name":"CQ025","deviceID":"1609648"},{"account_id":"226860","deviceDesc":"1302193","name":"T009-O","deviceID":"1609433"},{"account_id":"226860","deviceDesc":"1303882","name":"G43","deviceID":"1609963"},{"account_id":"226860","deviceDesc":"1302226","name":"L014","deviceID":"1609436"},{"account_id":"226860","deviceDesc":"1304058","name":"L002","deviceID":"1610045"},{"account_id":"226860","deviceDesc":"1302834","name":"T283","deviceID":"1609836"},{"account_id":"226860","deviceDesc":"1302137","name":"T143","deviceID":"1609424"},{"account_id":"226860","deviceDesc":"1303639","name":"T014","deviceID":"1609928"},{"account_id":"226860","deviceDesc":"1302785","name":"CQ023","deviceID":"1609515"},{"account_id":"226860","deviceDesc":"1301842","name":"F011","deviceID":"1609403"},{"account_id":"226860","deviceDesc":"1302822","name":"G40","deviceID":"1609742"},{"account_id":"226860","deviceDesc":"1290744","name":"F001","deviceID":"643522"},{"account_id":"226860","deviceDesc":"1290030","name":"T100","deviceID":"643340"},{"account_id":"226860","deviceDesc":"1300739","name":"T188","deviceID":"2259156"},{"account_id":"226860","deviceDesc":"1303964","name":"T272","deviceID":"2259285"},{"account_id":"226860","deviceDesc":"1285732","name":"T243","deviceID":"232062"},{"account_id":"226860","deviceDesc":"1300770","name":"CQ035","deviceID":"1604037"},{"account_id":"226860","deviceDesc":"1300540","name":"SMC006","deviceID":"3529012"},{"account_id":"226860","deviceDesc":"1287280","name":"F003","deviceID":"1602753"},{"account_id":"226860","deviceDesc":"1292069","name":"T229","deviceID":"643677"}]}]